[
  {"date": "2025-09-01", "China": 42, "India": 30, "Vietnam": 24},
  {"date": "2025-09-10", "China": 44, "India": 31, "Vietnam": 25},
  {"date": "2025-09-20", "China": 45, "India": 32, "Vietnam": 26},
  {"date": "2025-10-01", "China": 47, "India": 33, "Vietnam": 27},
  {"date": "2025-10-10", "China": 49, "India": 34, "Vietnam": 28},
  {"date": "2025-10-20", "China": 50, "India": 35, "Vietnam": 29},
  {"date": "2025-11-01", "China": 48, "India": 34, "Vietnam": 28},
  {"date": "2025-11-10", "China": 51, "India": 35, "Vietnam": 29},
  {"date": "2025-11-20", "China": 53, "India": 36, "Vietnam": 30},
  {"date": "2025-12-01", "China": 55, "India": 37, "Vietnam": 31},
  {"date": "2025-12-10", "China": 57, "India": 38, "Vietnam": 32},
  {"date": "2025-12-20", "China": 59, "India": 39, "Vietnam": 33},
  {"date": "2026-01-01", "China": 55, "India": 38, "Vietnam": 30},
  {"date": "2026-01-10", "China": 60, "India": 40, "Vietnam": 34},
  {"date": "2026-01-20", "China": 63, "India": 41, "Vietnam": 36},
  {"date": "2026-02-01", "China": 67, "India": 42, "Vietnam": 38},
  {"date": "2026-02-10", "China": 70, "India": 44, "Vietnam": 40},
  {"date": "2026-02-20", "China": 73, "India": 45, "Vietnam": 42},
  {"date": "2026-03-01", "China": 75, "India": 46, "Vietnam": 44},
  {"date": "2026-03-10", "China": 72, "India": 44, "Vietnam": 41},
  {"date": "2026-03-20", "China": 74, "India": 45, "Vietnam": 43},
  {"date": "2026-04-01", "China": 78, "India": 47, "Vietnam": 45},
  {"date": "2026-04-10", "China": 80, "India": 48, "Vietnam": 47},
  {"date": "2026-04-20", "China": 82, "India": 50, "Vietnam": 49},
  {"date": "2026-05-01", "China": 85, "India": 52, "Vietnam": 50},
  {"date": "2026-05-10", "China": 83, "India": 50, "Vietnam": 48},
  {"date": "2026-05-20", "China": 86, "India": 53, "Vietnam": 51},
  {"date": "2026-06-01", "China": 88, "India": 55, "Vietnam": 53},
  {"date": "2026-06-10", "China": 90, "India": 57, "Vietnam": 55}
]